[

    {
        "model": "meals.Meal",
        "fields": {
            "name": "3 baci Dolma",
            "price": "5.00"
        }
    },
    {
        "model": "meals.Meal",
        "fields": {
            "name": "As Qara",
            "price": "5.00"
        }
    },
    {
        "model": "meals.Meal",
        "fields": {
            "name": "As Qara 0.5",
            "price": "3.00"
        }
    },
    {
        "model": "meals.Meal",
        "fields": {
            "name": "Buglama",
            "price": "5.00"
        }
    },
    {
        "model": "meals.Meal",
        "fields": {
            "name": "Buglama 0.5",
            "price": "3.00"
        }
    },
    {
        "model": "meals.Meal",
        "fields": {
            "name": "Choban qovurma",
            "price": "5.00"
        }
    },
    {
        "model": "meals.Meal",
        "fields": {
            "name": "Choban qovurma 0.5",
            "price": "3.00"
        }
    },
    {
        "model": "meals.Meal",
        "fields": {
            "name": "Ciqirtma",
            "price": "5.00"
        }
    },
    {
        "model": "meals.Meal",
        "fields": {
            "name": "Ciqirtma (0.5)",
            "price": "3.00"
        }
    },
    {
        "model": "meals.Meal",
        "fields": {
            "name": "Ciz-biz",
            "price": "5.00"
        }
    },
    {
        "model": "meals.Meal",
        "fields": {
            "name": "Ciz-biz 0.5",
            "price": "3.00"
        }
    },
    {
        "model": "meals.Meal",
        "fields": {
            "name": "Dolma",
            "price": "5.00"
        }
    },
    {
        "model": "meals.Meal",
        "fields": {
            "name": "Dolma 0.5",
            "price": "3.00"
        }
    },
    {
        "model": "meals.Meal",
        "fields": {
            "name": "Doseme Plov",
            "price": "5.00"
        }
    },
    {
        "model": "meals.Meal",
        "fields": {
            "name": "Doseme Plov 0.5",
            "price": "3.00"
        }
    },
    {
        "model": "meals.Meal",
        "fields": {
            "name": "GOBELEKLI DANA qovurma",
            "price": "5.00"
        }
    },
    {
        "model": "meals.Meal",
        "fields": {
            "name": "GOBELEKLI DANA qovurma 0.5",
            "price": "3.00"
        }
    },
    {
        "model": "meals.Meal",
        "fields": {
            "name": "Imishli qovurma",
            "price": "5.00"
        }
    },
    {
        "model": "meals.Meal",
        "fields": {
            "name": "Imishli qovurma 0.5",
            "price": "3.00"
        }
    },
    {
        "model": "meals.Meal",
        "fields": {
            "name": "IZ QARA",
            "price": "4.00"
        }
    },
    {
        "model": "meals.Meal",
        "fields": {
            "name": "Jarko",
            "price": "5.00"
        }
    },
    {
        "model": "meals.Meal",
        "fields": {
            "name": "Jarko 0.5",
            "price": "3.00"
        }
    },
    {
        "model": "meals.Meal",
        "fields": {
            "name": "JULYEN",
            "price": "5.00"
        }
    },
    {
        "model": "meals.Meal",
        "fields": {
            "name": "Langet",
            "price": "4.00"
        }
    },
    {
        "model": "meals.Meal",
        "fields": {
            "name": "LEVENGI rulet",
            "price": "5.00"
        }
    },
    {
        "model": "meals.Meal",
        "fields": {
            "name": "LEVENGI toyuq0.5",
            "price": "6.00"
        }
    },
    {
        "model": "meals.Meal",
        "fields": {
            "name": "MANASTR",
            "price": "5.00"
        }
    },
    {
        "model": "meals.Meal",
        "fields": {
            "name": "Nar Qovurma",
            "price": "5.00"
        }
    },
    {
        "model": "meals.Meal",
        "fields": {
            "name": "Nar Qovurma 0.5",
            "price": "3.00"
        }
    },
    {
        "model": "meals.Meal",
        "fields": {
            "name": "Ozbek Ashi",
            "price": "4.00"
        }
    },
    {
        "model": "meals.Meal",
        "fields": {
            "name": "Ozbek Ashi 0.5",
            "price": "3.00"
        }
    },
    {
        "model": "meals.Meal",
        "fields": {
            "name": "Piti",
            "price": "6.00"
        }
    },
    {
        "model": "meals.Meal",
        "fields": {
            "name": "Qaymaqli Toyuq",
            "price": "5.00"
        }
    },
    {
        "model": "meals.Meal",
        "fields": {
            "name": "Qaymaqli Toyuq 0.5",
            "price": "3.00"
        }
    },
    {
        "model": "meals.Meal",
        "fields": {
            "name": "QULYAJ (et) 0.5",
            "price": "3.00"
        }
    },
    {
        "model": "meals.Meal",
        "fields": {
            "name": "QULYAJ (et)",
            "price": "5.00"
        }
    },
    {
        "model": "meals.Meal",
        "fields": {
            "name": "QULYAJ (toyuq)",
            "price": "5.00"
        }
    },
    {
        "model": "meals.Meal",
        "fields": {
            "name": "QULYAJ (toyuq) 0.5",
            "price": "3.00"
        }
    },
    {
        "model": "meals.Meal",
        "fields": {
            "name": "Sac ici (toyuq)",
            "price": "5.00"
        }
    },
    {
        "model": "meals.Meal",
        "fields": {
            "name": "Sac ici (toyuq) 0.5",
            "price": "3.00"
        }
    },
    {
        "model": "meals.Meal",
        "fields": {
            "name": "SAH Plov",
            "price": "5.00"
        }
    },
    {
        "model": "meals.Meal",
        "fields": {
            "name": "Sireli dana qovurma",
            "price": "5.00"
        }
    },
    {
        "model": "meals.Meal",
        "fields": {
            "name": "Sireli dana qovurma 0.5",
            "price": "3.00"
        }
    },
    {
        "model": "meals.Meal",
        "fields": {
            "name": "Tabaka 1/4",
            "price": "3.00"
        }
    },
    {
        "model": "meals.Meal",
        "fields": {
            "name": "Tabaka Tam",
            "price": "10.00"
        }
    },
    {
        "model": "meals.Meal",
        "fields": {
            "name": "Tabaka1/2",
            "price": "5.00"
        }
    },
    {
        "model": "meals.Meal",
        "fields": {
            "name": "Toyuq kotlet 1ed",
            "price": "1.50"
        }
    },
    {
        "model": "meals.Meal",
        "fields": {
            "name": "Toyuq Souzu",
            "price": "4.00"
        }
    },
    {
        "model": "meals.Meal",
        "fields": {
            "name": "Toyuq Souzu 0.5",
            "price": "2.50"
        }
    },
    {
        "model": "meals.Meal",
        "fields": {
            "name": "Toyuqlu Duyu",
            "price": "5.00"
        }
    },
    {
        "model": "meals.Meal",
        "fields": {
            "name": "Toyuqlu Duyu 0.5",
            "price": "3.00"
        }
    },
    {
        "model": "meals.Meal",
        "fields": {
            "name": "TSONKA",
            "price": "5.00"
        }
    },
    {
        "model": "meals.Meal",
        "fields": {
            "name": "TSONKA 0.5",
            "price": "3.00"
        }
    },
    {
        "model": "meals.Meal",
        "fields": {
            "name": "Tursulu Et Qovurma",
            "price": "5.00"
        }
    },
    {
        "model": "meals.Meal",
        "fields": {
            "name": "Tursulu et qovurma 0.5",
            "price": "3.00"
        }
    },
    {
        "model": "meals.Meal",
        "fields": {
            "name": "Tursulu Toyuq",
            "price": "5.00"
        }
    },
    {
        "model": "meals.Meal",
        "fields": {
            "name": "Tursulu Toyuq",
            "price": "3.00"
        }
    }
]
